gmutils/__init__.py
gmutils/__version__.py
gmutils/helpers/__init__.py
gmutils/helpers/helpme_argument.py
gmutils/helpers/helpme_log.py
gmutils/helpers/helpme_printing.py
gmutils/helpers/helpme_thread.py
gmutils/utils/__init__.py
gmutils/utils/config.py
gmutils/utils/constants.py
gmutils/utils/exceptions.py
gmutils/utils/get.py
gmutils/utils/paths.py
gmutils-0.1.3.dist-info/DESCRIPTION.rst
gmutils-0.1.3.dist-info/METADATA
gmutils-0.1.3.dist-info/RECORD
gmutils-0.1.3.dist-info/WHEEL
gmutils-0.1.3.dist-info/metadata.json
gmutils-0.1.3.dist-info/top_level.txt
