Metadata-Version: 2.0
Name: gmutils
Version: 0.1.3
Summary: GeekMasher's Open Source Python Utilities Library
Home-page: https://github.com/GeekMasher/GMUtils
Author: GeekMasher
Author-email: geekmasher@gmail.com
License: MIT License
Project-URL: Source Code, https://github.com/GeekMasher/GMUtils
Project-URL: Bug Tracker, https://github.com/GeekMasher/GMUtils/issues
Platform: UNKNOWN
Classifier: Development Status :: 5 - Production/Stable
Classifier: Environment :: Console
Classifier: Environment :: Web Environment
Classifier: Intended Audience :: End Users/Desktop
Classifier: Intended Audience :: Developers
Classifier: Intended Audience :: System Administrators
Classifier: License :: OSI Approved :: MIT License
Classifier: Natural Language :: English
Classifier: Operating System :: MacOS
Classifier: Operating System :: Microsoft :: Windows
Classifier: Operating System :: POSIX
Classifier: Operating System :: POSIX :: Linux
Classifier: Programming Language :: Python :: 3
Classifier: Programming Language :: Python :: 3.6
